__init__.py
container/cont.py
probst-0.0.3.dist-info/LICENSE
probst-0.0.3.dist-info/METADATA
probst-0.0.3.dist-info/WHEEL
probst-0.0.3.dist-info/top_level.txt
probst-0.0.3.dist-info/RECORD
