Metadata-Version: 2.1
Name: probst
Version: 0.0.3
Summary: Probability and Statistics toolbox
Author-email: Soheil Soltani <soheil@netc.eu>
Project-URL: Homepage, https://github.com/soheil-soltani/probst
Classifier: Programming Language :: Python :: 3
Classifier: License :: OSI Approved :: MIT License
Classifier: Operating System :: OS Independent
Requires-Python: >=3.7
License-File: LICENSE
